.gitignore
LICENSE
README.md
setup.py
ghelpers/__init__.py
ghelpers.egg-info/PKG-INFO
ghelpers.egg-info/SOURCES.txt
ghelpers.egg-info/dependency_links.txt
ghelpers.egg-info/requires.txt
ghelpers.egg-info/top_level.txt