Metadata-Version: 2.1
Name: ghelpers
Version: 0.2
Summary: Grouping of common functions used in Google Cloud Platform, intended to help other processes.
Home-page: https://github.com/rimedinaz/ghelpers
Author: Richard Medina
Author-email: rimedinaz@gmail.com
License: Apache License 2.0
Platform: UNKNOWN
Classifier: Programming Language :: Python :: 3
Classifier: License :: OSI Approved :: Apache Software License
Classifier: Operating System :: OS Independent
Requires-Python: >=3.4.*
Provides-Extra: secretmanager
License-File: LICENSE
